LICENSE
MANIFEST.in
README.md
requirements.txt
setup.py
mimic3_http/VERSION
mimic3_http/__init__.py
mimic3_http/__main__.py
mimic3_http/_resources.py
mimic3_http/app.py
mimic3_http/args.py
mimic3_http/const.py
mimic3_http/py.typed
mimic3_http/synthesis.py
mimic3_http/css/bootstrap.min.css
mimic3_http/img/Mimic_color.png
mimic3_http/img/Mycroft_logo_two_typeonly.png
mimic3_http/img/favicon.png
mimic3_http/templates/index.html
mimic3_tts/VERSION
mimic3_tts/__init__.py
mimic3_tts/__main__.py
mimic3_tts/_resources.py
mimic3_tts/config.py
mimic3_tts/const.py
mimic3_tts/download.py
mimic3_tts/py.typed
mimic3_tts/tts.py
mimic3_tts/utils.py
mimic3_tts/voice.py
mimic3_tts/voices.json
mycroft_mimic3_tts.egg-info/PKG-INFO
mycroft_mimic3_tts.egg-info/SOURCES.txt
mycroft_mimic3_tts.egg-info/dependency_links.txt
mycroft_mimic3_tts.egg-info/entry_points.txt
mycroft_mimic3_tts.egg-info/requires.txt
mycroft_mimic3_tts.egg-info/top_level.txt
opentts_abc/VERSION
opentts_abc/__init__.py
opentts_abc/py.typed
opentts_abc/ssml.py