Metadata-Version: 2.1
Name: mycroft-mimic3-tts
Version: 0.2.2
Summary: A fast and local neural text to speech system for Mycroft
Home-page: http://github.com/MycroftAI/mimic3
Author: Michael Hansen
Author-email: michael.hansen@mycroft.ai
License: AGPLv3+
Keywords: mycroft tts speech mimic
Platform: UNKNOWN
Classifier: Development Status :: 3 - Alpha
Classifier: Intended Audience :: Developers
Classifier: Topic :: Text Processing :: Linguistic
Classifier: License :: OSI Approved :: GNU Affero General Public License v3
Classifier: Programming Language :: Python :: 3.7
Classifier: Programming Language :: Python :: 3.8
Classifier: Programming Language :: Python :: 3.9
Provides-Extra: all
Provides-Extra: de
Provides-Extra: es
Provides-Extra: fa
Provides-Extra: fr
Provides-Extra: it
Provides-Extra: nl
Provides-Extra: ru
Provides-Extra: sw
